{"Pression": {"img": "https://static.ankama.com/dofus/ng/img/../../../dofus/www/game/spells/55/sort_141.png", "id": "13106", "nom_variante": "Fracture", "1": {"PO_min": "1", "PO_max": "3", "PA": "3", "level": "1", "Effets": ["10% \u00c9rosion (2 tours)", "14 \u00e0 17 (dommages Terre)"], "EffetsCritiques": ["10% \u00c9rosion (2 tours)", "17 \u00e0 20 (dommages Terre)"], "Autres": {"Probabilit\u00e9 de coup critique": "5%", "Nb. de lancers par tour par joueur": "2", "Port\u00e9e modifiable": "Non", "Ligne de vue": "Oui", "Lancer en ligne": "Non", "Cellules libres": "Non"}}, "desc": "Occasionne des dommages Terre et applique un malus d'\u00c9rosion.", "2": {"PO_min": "1", "PO_max": "3", "PA": "3", "level": "66", "Effets": ["10% \u00c9rosion (2 tours)", "19 \u00e0 22 (dommages Terre)"], "EffetsCritiques": ["10% \u00c9rosion (2 tours)", "22 \u00e0 26 (dommages Terre)"], "Autres": {"Probabilit\u00e9 de coup critique": "5%", "Nb. de lancers par tour par joueur": "2", "Port\u00e9e modifiable": "Non", "Ligne de vue": "Oui", "Lancer en ligne": "Non", "Cellules libres": "Non"}}, "3": {"PO_min": "1", "PO_max": "3", "PA": "3", "level": "132", "Effets": ["10% \u00c9rosion (2 tours)", "24 \u00e0 28 (dommages Terre)"], "EffetsCritiques": ["10% \u00c9rosion (2 tours)", "29 \u00e0 34 (dommages Terre)"], "Autres": {"Probabilit\u00e9 de coup critique": "5%", "Nb. de lancers par tour par joueur": "3", "Port\u00e9e modifiable": "Non", "Ligne de vue": "Oui", "Lancer en ligne": "Non", "Cellules libres": "Non"}}}, "Fracture": {"img": "https://static.ankama.com/dofus/ng/img/../../../dofus/www/game/spells/55/sort_3742.png", "id": "13139", "nom_variante": "Pression", "1": {"PO_min": "1", "PO_max": "4", "PA": "4", "level": "95", "Effets": ["13% \u00c9rosion (2 tours)", "27 \u00e0 31 (dommages Air)"], "EffetsCritiques": ["13% \u00c9rosion (2 tours)", "33 \u00e0 37 (dommages Air)"], "Autres": {"Probabilit\u00e9 de coup critique": "15%", "Nb. de lancers par tour": "2", "Port\u00e9e modifiable": "Non", "Ligne de vue": "Non", "Lancer en ligne": "Oui", "Cellules libres": "Non"}}, "desc": "Occasionne des dommages Air jusqu'\u00e0 la cellule cibl\u00e9e.\r\nApplique un malus d'\u00c9rosion.", "2": {"PO_min": "1", "PO_max": "4", "PA": "4", "level": "162", "Effets": ["13% \u00c9rosion (2 tours)", "34 \u00e0 38 (dommages Air)"], "EffetsCritiques": ["13% \u00c9rosion (2 tours)", "41 \u00e0 46 (dommages Air)"], "Autres": {"Probabilit\u00e9 de coup critique": "15%", "Nb. de lancers par tour": "2", "Port\u00e9e modifiable": "Non", "Ligne de vue": "Non", "Lancer en ligne": "Oui", "Cellules libres": "Non"}}}, "Bond": {"img": "https://static.ankama.com/dofus/ng/img/../../../dofus/www/game/spells/55/sort_142.png", "id": "13107", "nom_variante": "D\u00e9termination", "1": {"PO_min": "1", "PO_max": "5", "PA": "5", "level": "1", "Effets": ["T\u00e9l\u00e9porte sur la case cibl\u00e9e", "Dommages subis x115%"], "EffetsCritiques": ["T\u00e9l\u00e9porte sur la case cibl\u00e9e", "Dommages subis x120%"], "Autres": {"Probabilit\u00e9 de coup critique": "15%", "Nb. de tours entre deux lancers": "2", "Port\u00e9e modifiable": "Non", "Ligne de vue": "Non", "Lancer en ligne": "Non", "Cellules libres": "Oui", "Zone d'effet": "Croix de 1 case"}}, "desc": "T\u00e9l\u00e9porte sur la case cibl\u00e9e.\r\nAugmente les dommages re\u00e7us par les ennemis situ\u00e9s sur les cases adjacentes.", "2": {"PO_min": "1", "PO_max": "5", "PA": "5", "level": "67", "Effets": ["T\u00e9l\u00e9porte sur la case cibl\u00e9e", "Dommages subis x115%"], "EffetsCritiques": ["T\u00e9l\u00e9porte sur la case cibl\u00e9e", "Dommages subis x120%"], "Autres": {"Probabilit\u00e9 de coup critique": "15%", "Nb. de tours entre deux lancers": "1", "Port\u00e9e modifiable": "Non", "Ligne de vue": "Non", "Lancer en ligne": "Non", "Cellules libres": "Oui", "Zone d'effet": "Croix de 1 case"}}, "3": {"PO_min": "1", "PO_max": "6", "PA": "5", "level": "133", "Effets": ["T\u00e9l\u00e9porte sur la case cibl\u00e9e", "Dommages subis x115%"], "EffetsCritiques": ["T\u00e9l\u00e9porte sur la case cibl\u00e9e", "Dommages subis x120%"], "Autres": {"Probabilit\u00e9 de coup critique": "15%", "Nb. de lancers par tour": "1", "Port\u00e9e modifiable": "Non", "Ligne de vue": "Non", "Lancer en ligne": "Non", "Cellules libres": "Oui", "Zone d'effet": "Croix de 1 case"}}}, "D\u00e9termination": {"img": "https://static.ankama.com/dofus/ng/img/../../../dofus/www/game/spells/55/sort_3731.png", "id": "13132", "nom_variante": "Bond", "1": {"PO_min": "0", "PO_max": "0", "PA": "3", "level": "100", "Effets": ["\u00c9tat 'Ind\u00e9pla\u00e7able' (1 tour)", "Dommages subis x75%"], "EffetsCritiques": [], "Autres": {"Nb. de lancers par tour": "1", "Nb. de tours entre deux lancers": "2", "Port\u00e9e modifiable": "Non", "Ligne de vue": "Non", "Lancer en ligne": "Non", "Cellules libres": "Non"}}, "desc": "Fixe l'\u00e9tat Ind\u00e9pla\u00e7able et r\u00e9duit 25% des dommages subis pendant 1 tour.\r\nNe peut pas \u00eatre d\u00e9senvo\u00fbt\u00e9.", "2": {"PO_min": "0", "PO_max": "0", "PA": "2", "level": "167", "Effets": ["\u00c9tat 'Ind\u00e9pla\u00e7able' (1 tour)", "Dommages subis x75%"], "EffetsCritiques": [], "Autres": {"Nb. de lancers par tour": "1", "Nb. de tours entre deux lancers": "2", "Port\u00e9e modifiable": "Non", "Ligne de vue": "Non", "Lancer en ligne": "Non", "Cellules libres": "Non"}}}, "D\u00e9ferlement": {"img": "https://static.ankama.com/dofus/ng/img/../../../dofus/www/game/spells/55/sort_410.png", "id": "13126", "nom_variante": "Anneau Destructeur", "1": {"PO_min": "0", "PO_max": "5", "PA": "4", "level": "1", "Effets": ["Avance de 4 case(s)", "23 \u00e0 25 (dommages Eau)", "50% du niveau en bouclier (2 tours)"], "EffetsCritiques": ["Avance de 4 case(s)", "27 \u00e0 30 (dommages Eau)", "50% du niveau en bouclier (2 tours)"], "Autres": {"Probabilit\u00e9 de coup critique": "5%", "Nb. de lancers par tour": "3", "Nb. de lancers par tour par joueur": "2", "Port\u00e9e modifiable": "Non", "Ligne de vue": "Oui", "Lancer en ligne": "Oui", "Cellules libres": "Non"}}, "desc": "Occasionne des dommages Eau aux ennemis et rapproche le lanceur de la cible.\r\nLe lanceur gagne des points de bouclier.", "2": {"PO_min": "0", "PO_max": "5", "PA": "4", "level": "68", "Effets": ["Avance de 4 case(s)", "30 \u00e0 33 (dommages Eau)", "50% du niveau en bouclier (2 tours)"], "EffetsCritiques": ["Avance de 4 case(s)", "36 \u00e0 39 (dommages Eau)", "50% du niveau en bouclier (2 tours)"], "Autres": {"Probabilit\u00e9 de coup critique": "5%", "Nb. de lancers par tour": "3", "Nb. de lancers par tour par joueur": "2", "Port\u00e9e modifiable": "Non", "Ligne de vue": "Oui", "Lancer en ligne": "Oui", "Cellules libres": "Non"}}, "3": {"PO_min": "0", "PO_max": "5", "PA": "4", "level": "134", "Effets": ["Avance de 4 case(s)", "38 \u00e0 42 (dommages Eau)", "50% du niveau en bouclier (2 tours)"], "EffetsCritiques": ["Avance de 4 case(s)", "46 \u00e0 50 (dommages Eau)", "50% du niveau en bouclier (2 tours)"], "Autres": {"Probabilit\u00e9 de coup critique": "5%", "Nb. de lancers par tour": "3", "Nb. de lancers par tour par joueur": "2", "Port\u00e9e modifiable": "Non", "Ligne de vue": "Oui", "Lancer en ligne": "Oui", "Cellules libres": "Non"}}}, "Anneau Destructeur": {"img": "https://static.ankama.com/dofus/ng/img/../../../dofus/www/game/spells/55/sort_3727.png", "id": "13135", "nom_variante": "D\u00e9ferlement", "1": {"PO_min": "0", "PO_max": "2", "PA": "3", "level": "105", "Effets": ["23 \u00e0 26 (dommages Air)", "Attire de 1 case(s)"], "EffetsCritiques": ["27 \u00e0 31 (dommages Air)", "Attire de 1 case(s)"], "Autres": {"Probabilit\u00e9 de coup critique": "15%", "Nb. de lancers par tour": "1", "Port\u00e9e modifiable": "Non", "Ligne de vue": "Oui", "Lancer en ligne": "Non", "Cellules libres": "Non", "Zone d'effet": "Anneau de 3 cases"}}, "desc": "Occasionne des dommages Air en anneau et attire les cibles.", "2": {"PO_min": "0", "PO_max": "2", "PA": "3", "level": "172", "Effets": ["26 \u00e0 30 (dommages Air)", "Attire de 1 case(s)"], "EffetsCritiques": ["31 \u00e0 36 (dommages Air)", "Attire de 1 case(s)"], "Autres": {"Probabilit\u00e9 de coup critique": "15%", "Nb. de lancers par tour": "2", "Port\u00e9e modifiable": "Non", "Ligne de vue": "Oui", "Lancer en ligne": "Non", "Cellules libres": "Non", "Zone d'effet": "Anneau de 3 cases"}}}, "\u00c9p\u00e9e Divine": {"img": "https://static.ankama.com/dofus/ng/img/../../../dofus/www/game/spells/55/sort_145.png", "id": "13110", "nom_variante": "Couperet", "1": {"PO_min": "0", "PO_max": "0", "PA": "3", "level": "3", "Effets": ["12 \u00e0 14 (dommages Air)", "10 Dommages (4 tours)"], "EffetsCritiques": ["15 \u00e0 17 (dommages Air)", "13 Dommages (4 tours)"], "Autres": {"Probabilit\u00e9 de coup critique": "5%", "Nb. de lancers par tour": "2", "Port\u00e9e modifiable": "Non", "Ligne de vue": "Non", "Lancer en ligne": "Non", "Cellules libres": "Non", "Zone d'effet": "Croix de 3 cases"}}, "desc": "Occasionne des dommages Air et augmente les dommages des alli\u00e9s cibl\u00e9s.", "2": {"PO_min": "0", "PO_max": "0", "PA": "3", "level": "69", "Effets": ["17 \u00e0 19 (dommages Air)", "15 Dommages (4 tours)"], "EffetsCritiques": ["20 \u00e0 22 (dommages Air)", "18 Dommages (4 tours)"], "Autres": {"Probabilit\u00e9 de coup critique": "5%", "Nb. de lancers par tour": "2", "Port\u00e9e modifiable": "Non", "Ligne de vue": "Non", "Lancer en ligne": "Non", "Cellules libres": "Non", "Zone d'effet": "Croix de 3 cases"}}, "3": {"PO_min": "0", "PO_max": "0", "PA": "3", "level": "136", "Effets": ["21 \u00e0 23 (dommages Air)", "20 Dommages (4 tours)"], "EffetsCritiques": ["25 \u00e0 28 (dommages Air)", "23 Dommages (4 tours)"], "Autres": {"Probabilit\u00e9 de coup critique": "5%", "Nb. de lancers par tour": "2", "Port\u00e9e modifiable": "Non", "Ligne de vue": "Non", "Lancer en ligne": "Non", "Cellules libres": "Non", "Zone d'effet": "Croix de 3 cases"}}}, "Couperet": {"img": "https://static.ankama.com/dofus/ng/img/../../../dofus/www/game/spells/55/sort_150.png", "id": "13115", "nom_variante": "\u00c9p\u00e9e Divine", "1": {"PO_min": "1", "PO_max": "3", "PA": "3", "level": "110", "Effets": ["17 \u00e0 19 (dommages Feu)", "-2 PM (1 tour)"], "EffetsCritiques": ["20 \u00e0 22 (dommages Feu)", "-2 PM (1 tour)"], "Autres": {"Probabilit\u00e9 de coup critique": "5%", "Nb. de lancers par tour": "2", "Port\u00e9e modifiable": "Oui", "Ligne de vue": "Oui", "Lancer en ligne": "Oui", "Cellules libres": "Non", "Zone d'effet": "Ligne de 3 cases"}}, "desc": "Occasionne des dommages Feu et retire des PM.", "2": {"PO_min": "1", "PO_max": "4", "PA": "3", "level": "177", "Effets": ["21 \u00e0 23 (dommages Feu)", "-3 PM (1 tour)"], "EffetsCritiques": ["25 \u00e0 28 (dommages Feu)", "-3 PM (1 tour)"], "Autres": {"Probabilit\u00e9 de coup critique": "5%", "Nb. de lancers par tour": "2", "Port\u00e9e modifiable": "Oui", "Ligne de vue": "Oui", "Lancer en ligne": "Oui", "Cellules libres": "Non", "Zone d'effet": "Ligne de 3 cases"}}}, "\u00c9p\u00e9e Destructrice": {"img": "https://static.ankama.com/dofus/ng/img/../../../dofus/www/game/spells/55/sort_154.png", "id": "13119", "nom_variante": "Accumulation", "1": {"PO_min": "1", "PO_max": "5", "PA": "4", "level": "6", "Effets": ["19 \u00e0 22 (dommages Feu)"], "EffetsCritiques": ["23 \u00e0 26 (dommages Feu)"], "Autres": {"Probabilit\u00e9 de coup critique": "15%", "Nb. de lancers par tour": "2", "Port\u00e9e modifiable": "Non", "Ligne de vue": "Oui", "Lancer en ligne": "Oui", "Cellules libres": "Non", "Zone d'effet": "Ligne perpendiculaire de 1 case"}}, "desc": "Occasionne des dommages Feu en zone.", "2": {"PO_min": "1", "PO_max": "5", "PA": "4", "level": "71", "Effets": ["26 \u00e0 29 (dommages Feu)"], "EffetsCritiques": ["31 \u00e0 35 (dommages Feu)"], "Autres": {"Probabilit\u00e9 de coup critique": "15%", "Nb. de lancers par tour": "2", "Port\u00e9e modifiable": "Non", "Ligne de vue": "Oui", "Lancer en ligne": "Oui", "Cellules libres": "Non", "Zone d'effet": "Ligne perpendiculaire de 1 case"}}, "3": {"PO_min": "1", "PO_max": "5", "PA": "4", "level": "138", "Effets": ["32 \u00e0 36 (dommages Feu)"], "EffetsCritiques": ["38 \u00e0 43 (dommages Feu)"], "Autres": {"Probabilit\u00e9 de coup critique": "15%", "Nb. de lancers par tour": "2", "Port\u00e9e modifiable": "Non", "Ligne de vue": "Oui", "Lancer en ligne": "Oui", "Cellules libres": "Non", "Zone d'effet": "Ligne perpendiculaire de 1 case"}}}, "Accumulation": {"img": "https://static.ankama.com/dofus/ng/img/../../../dofus/www/game/spells/55/sort_3736.png", "id": "13138", "nom_variante": "\u00c9p\u00e9e Destructrice", "1": {"PO_min": "0", "PO_max": "4", "PA": "3", "level": "115", "Effets": ["Accumulation", "19 \u00e0 22 (dommages Terre)", "Accumulation", "Augmente les d\u00e9g\u00e2ts de base du sort Accumulation de 20 (3 tours)"], "EffetsCritiques": ["Accumulation", "22 \u00e0 27 (dommages Terre)", "Accumulation", "Augmente les d\u00e9g\u00e2ts de base du sort Accumulation de 24 (3 tours)"], "Autres": {"Probabilit\u00e9 de coup critique": "5%", "Nb. de lancers par tour": "3", "Nb. de lancers par tour par joueur": "2", "Port\u00e9e modifiable": "Non", "Ligne de vue": "Oui", "Lancer en ligne": "Oui", "Cellules libres": "Non"}}, "desc": "Occasionne des dommages Terre.\r\nSi le sort est lanc\u00e9 sur soi, le sort n'occasionne pas de dommages et ils sont augment\u00e9s pour les prochains lancers.", "2": {"PO_min": "0", "PO_max": "4", "PA": "3", "level": "182", "Effets": ["Accumulation", "22 \u00e0 26 (dommages Terre)", "Accumulation", "Augmente les d\u00e9g\u00e2ts de base du sort Accumulation de 20 (3 tours)"], "EffetsCritiques": ["Accumulation", "26 \u00e0 31 (dommages Terre)", "Accumulation", "Augmente les d\u00e9g\u00e2ts de base du sort Accumulation de 24 (3 tours)"], "Autres": {"Probabilit\u00e9 de coup critique": "5%", "Nb. de lancers par tour": "3", "Nb. de lancers par tour par joueur": "2", "Port\u00e9e modifiable": "Non", "Ligne de vue": "Oui", "Lancer en ligne": "Oui", "Cellules libres": "Non"}}}, "Intimidation": {"img": "https://static.ankama.com/dofus/ng/img/../../../dofus/www/game/spells/55/sort_4152.png", "id": "13108", "nom_variante": "Conqu\u00eate", "1": {"PO_min": "1", "PO_max": "2", "PA": "2", "level": "10", "Effets": ["4 \u00e0 6 (dommages)", "Repousse de 2 case(s)"], "EffetsCritiques": ["5 \u00e0 7 (dommages)", "Repousse de 2 case(s)"], "Autres": {"Probabilit\u00e9 de coup critique": "5%", "Nb. de lancers par tour": "3", "Nb. de lancers par tour par joueur": "2", "Port\u00e9e modifiable": "Non", "Ligne de vue": "Oui", "Lancer en ligne": "Oui", "Cellules libres": "Non"}}, "desc": "Occasionne des dommages dans le meilleur \u00e9l\u00e9ment d'attaque du lanceur sur les ennemis et repousse la cible.", "2": {"PO_min": "1", "PO_max": "2", "PA": "2", "level": "77", "Effets": ["6 \u00e0 8 (dommages)", "Repousse de 3 case(s)"], "EffetsCritiques": ["8 \u00e0 10 (dommages)", "Repousse de 3 case(s)"], "Autres": {"Probabilit\u00e9 de coup critique": "5%", "Nb. de lancers par tour": "3", "Nb. de lancers par tour par joueur": "2", "Port\u00e9e modifiable": "Non", "Ligne de vue": "Oui", "Lancer en ligne": "Oui", "Cellules libres": "Non"}}, "3": {"PO_min": "1", "PO_max": "2", "PA": "2", "level": "144", "Effets": ["8 \u00e0 10 (dommages)", "Repousse de 3 case(s)"], "EffetsCritiques": ["10 \u00e0 12 (dommages)", "Repousse de 3 case(s)"], "Autres": {"Probabilit\u00e9 de coup critique": "5%", "Nb. de lancers par tour": "3", "Nb. de lancers par tour par joueur": "2", "Port\u00e9e modifiable": "Non", "Ligne de vue": "Oui", "Lancer en ligne": "Oui", "Cellules libres": "Non"}}}, "Conqu\u00eate": {"img": "https://static.ankama.com/dofus/ng/img/../../../dofus/www/game/spells/55/sort_3733.png", "id": "13148", "nom_variante": "Intimidation", "1": {"PO_min": "1", "PO_max": "5", "PA": "3", "level": "120", "Effets": ["Invoque : Strat\u00e8ge Iop", "Tue la cible"], "EffetsCritiques": [], "Autres": {"Nb. de tours entre deux lancers": "3", "Port\u00e9e modifiable": "Non", "Ligne de vue": "Oui", "Lancer en ligne": "Non", "Cellules libres": "Oui", "Zone d'effet": "Tout le monde"}}, "desc": "Invoque un Strat\u00e8ge qui redistribue \u00e0 proximit\u00e9 (2 cases) 50% des dommages de sort qu'il subit.", "2": {"PO_min": "1", "PO_max": "6", "PA": "3", "level": "187", "Effets": ["Invoque : Strat\u00e8ge Iop", "Tue la cible"], "EffetsCritiques": [], "Autres": {"Nb. de tours entre deux lancers": "3", "Port\u00e9e modifiable": "Non", "Ligne de vue": "Oui", "Lancer en ligne": "Non", "Cellules libres": "Oui", "Zone d'effet": "Tout le monde"}}}, "Souffle": {"img": "https://static.ankama.com/dofus/ng/img/../../../dofus/www/game/spells/55/sort_151.png", "id": "13116", "nom_variante": "Violence", "1": {"PO_min": "2", "PO_max": "4", "PA": "2", "level": "15", "Effets": ["Repousse de 1 case(s)"], "EffetsCritiques": [], "Autres": {"Nb. de tours entre deux lancers": "2", "Port\u00e9e modifiable": "Non", "Ligne de vue": "Non", "Lancer en ligne": "Non", "Cellules libres": "Non", "Zone d'effet": "Croix de 1 case"}}, "desc": "Repousse les alli\u00e9s et les ennemis situ\u00e9s autour de la cellule cibl\u00e9e.", "2": {"PO_min": "2", "PO_max": "6", "PA": "2", "level": "82", "Effets": ["Repousse de 1 case(s)"], "EffetsCritiques": [], "Autres": {"Nb. de tours entre deux lancers": "2", "Port\u00e9e modifiable": "Non", "Ligne de vue": "Non", "Lancer en ligne": "Non", "Cellules libres": "Non", "Zone d'effet": "Croix de 1 case"}}, "3": {"PO_min": "2", "PO_max": "8", "PA": "2", "level": "149", "Effets": ["Repousse de 1 case(s)"], "EffetsCritiques": [], "Autres": {"Nb. de tours entre deux lancers": "2", "Port\u00e9e modifiable": "Non", "Ligne de vue": "Non", "Lancer en ligne": "Non", "Cellules libres": "Non", "Zone d'effet": "Croix de 1 case"}}}, "Violence": {"img": "https://static.ankama.com/dofus/ng/img/../../../dofus/www/game/spells/55/sort_3741.png", "id": "13137", "nom_variante": "Souffle", "1": {"PO_min": "0", "PO_max": "0", "PA": "2", "level": "125", "Effets": ["Violence", "40 Dommages Pouss\u00e9e (1 tour)", "20 Tacle (1 tour)", "Attire de 1 case(s)"], "EffetsCritiques": [], "Autres": {"Nb. de lancers par tour": "1", "Port\u00e9e modifiable": "Non", "Ligne de vue": "Non", "Lancer en ligne": "Non", "Cellules libres": "Non", "Zone d'effet": "Cercle de 2 cases"}}, "desc": "Attire les entit\u00e9s \u00e0 proximit\u00e9 et augmente les dommages de pouss\u00e9e et le Tacle pour chaque ennemi dans la zone d'effet.", "2": {"PO_min": "0", "PO_max": "0", "PA": "2", "level": "192", "Effets": ["Violence", "50 Dommages Pouss\u00e9e (1 tour)", "25 Tacle (1 tour)", "Attire de 1 case(s)"], "EffetsCritiques": [], "Autres": {"Nb. de lancers par tour": "1", "Port\u00e9e modifiable": "Non", "Ligne de vue": "Non", "Lancer en ligne": "Non", "Cellules libres": "Non", "Zone d'effet": "Cercle de 2 cases"}}}, "Massacre": {"img": "https://static.ankama.com/dofus/ng/img/../../../dofus/www/game/spells/55/sort_147.png", "id": "13112", "nom_variante": "Rassemblement", "1": {"PO_min": "1", "PO_max": "3", "PA": "2", "level": "20", "Effets": ["Putsch"], "EffetsCritiques": [], "Autres": {"Nb. de tours entre deux lancers": "3", "Port\u00e9e modifiable": "Non", "Ligne de vue": "Oui", "Lancer en ligne": "Non", "Cellules libres": "Non"}}, "desc": "Lorsque la cible ennemie re\u00e7oit des dommages de sorts, elle occasionne 50% de ces dommages aux ennemis au contact.", "2": {"PO_min": "1", "PO_max": "5", "PA": "2", "level": "87", "Effets": ["Putsch"], "EffetsCritiques": [], "Autres": {"Nb. de tours entre deux lancers": "3", "Port\u00e9e modifiable": "Non", "Ligne de vue": "Oui", "Lancer en ligne": "Non", "Cellules libres": "Non"}}, "3": {"PO_min": "1", "PO_max": "7", "PA": "2", "level": "154", "Effets": ["Putsch"], "EffetsCritiques": [], "Autres": {"Nb. de tours entre deux lancers": "3", "Port\u00e9e modifiable": "Non", "Ligne de vue": "Oui", "Lancer en ligne": "Non", "Cellules libres": "Non"}}}, "Rassemblement": {"img": "https://static.ankama.com/dofus/ng/img/../../../dofus/www/game/spells/55/sort_3745.png", "id": "13136", "nom_variante": "Massacre", "1": {"PO_min": "0", "PO_max": "5", "PA": "2", "level": "130", "Effets": ["Rassemblement", "Attire de 2 case(s)"], "EffetsCritiques": [], "Autres": {"Nb. de tours entre deux lancers": "2", "Port\u00e9e modifiable": "Non", "Ligne de vue": "Oui", "Lancer en ligne": "Non", "Cellules libres": "Non", "Zone d'effet": "Croix de 3 cases"}}, "desc": "Rapproche les ennemis de la cible. \r\nSi la cible est un ennemi, elle attire ensuite ses alli\u00e9s quand elle est attaqu\u00e9e pendant 1 tour.", "2": {"PO_min": "0", "PO_max": "6", "PA": "2", "level": "197", "Effets": ["Rassemblement", "Attire de 2 case(s)"], "EffetsCritiques": [], "Autres": {"Nb. de tours entre deux lancers": "2", "Port\u00e9e modifiable": "Non", "Ligne de vue": "Oui", "Lancer en ligne": "Non", "Cellules libres": "Non", "Zone d'effet": "Croix de 3 cases"}}}, "Concentration": {"img": "https://static.ankama.com/dofus/ng/img/../../../dofus/www/game/spells/55/sort_158.png", "id": "13123", "nom_variante": "\u00c9p\u00e9e du Jugement", "1": {"PO_min": "1", "PO_max": "1", "PA": "2", "level": "25", "Effets": ["13 \u00e0 15 (dommages Terre)", "19 \u00e0 21 (dommages Terre)"], "EffetsCritiques": ["15 \u00e0 18 (dommages Terre)", "23 \u00e0 26 (dommages Terre)"], "Autres": {"Probabilit\u00e9 de coup critique": "5%", "Nb. de lancers par tour": "3", "Nb. de lancers par tour par joueur": "2", "Port\u00e9e modifiable": "Non", "Ligne de vue": "Oui", "Lancer en ligne": "Oui", "Cellules libres": "Non"}}, "desc": "Occasionne des dommages Terre.\r\nLes dommages sont augment\u00e9s contre les Invocations.", "2": {"PO_min": "1", "PO_max": "1", "PA": "2", "level": "92", "Effets": ["16 \u00e0 19 (dommages Terre)", "24 \u00e0 27 (dommages Terre)"], "EffetsCritiques": ["19 \u00e0 23 (dommages Terre)", "29 \u00e0 33 (dommages Terre)"], "Autres": {"Probabilit\u00e9 de coup critique": "5%", "Nb. de lancers par tour": "3", "Nb. de lancers par tour par joueur": "2", "Port\u00e9e modifiable": "Non", "Ligne de vue": "Oui", "Lancer en ligne": "Oui", "Cellules libres": "Non"}}, "3": {"PO_min": "1", "PO_max": "1", "PA": "2", "level": "159", "Effets": ["20 \u00e0 24 (dommages Terre)", "30 \u00e0 34 (dommages Terre)"], "EffetsCritiques": ["24 \u00e0 29 (dommages Terre)", "36 \u00e0 41 (dommages Terre)"], "Autres": {"Probabilit\u00e9 de coup critique": "5%", "Nb. de lancers par tour": "4", "Nb. de lancers par tour par joueur": "3", "Port\u00e9e modifiable": "Non", "Ligne de vue": "Oui", "Lancer en ligne": "Oui", "Cellules libres": "Non"}}}, "\u00c9p\u00e9e du Jugement": {"img": "https://static.ankama.com/dofus/ng/img/../../../dofus/www/game/spells/55/sort_4151.png", "id": "13117", "nom_variante": "Concentration", "1": {"PO_min": "1", "PO_max": "6", "PA": "4", "level": "135", "Effets": ["27 \u00e0 31 (dommages Eau)", "\u00c9p\u00e9e du Jugement", "Enl\u00e8ve les effets du sort \u00c9p\u00e9e du Jugement", "Enl\u00e8ve les effets du sort \u00c9p\u00e9e du Jugement", "Augmente les d\u00e9g\u00e2ts de base du sort \u00c9p\u00e9e du Jugement de 10 (infini)"], "EffetsCritiques": ["32 \u00e0 37 (dommages Eau)", "\u00c9p\u00e9e du Jugement", "Enl\u00e8ve les effets du sort \u00c9p\u00e9e du Jugement", "Enl\u00e8ve les effets du sort \u00c9p\u00e9e du Jugement", "Augmente les d\u00e9g\u00e2ts de base du sort \u00c9p\u00e9e du Jugement de 10 (infini)"], "Autres": {"Probabilit\u00e9 de coup critique": "5%", "Nb. de lancers par tour": "1", "Port\u00e9e modifiable": "Non", "Ligne de vue": "Non", "Lancer en ligne": "Non", "Cellules libres": "Non"}}, "desc": "Occasionne des dommages Eau sans ligne de vue. Les dommages sont augment\u00e9s \u00e0 chaque lancer. Si le lanceur subit des dommages en m\u00eal\u00e9e, les bonus de dommages sont retir\u00e9s.", "2": {"PO_min": "1", "PO_max": "6", "PA": "4", "level": "135", "Effets": ["27 \u00e0 31 (dommages Eau)", "\u00c9p\u00e9e du Jugement", "Enl\u00e8ve les effets du sort \u00c9p\u00e9e du Jugement", "Enl\u00e8ve les effets du sort \u00c9p\u00e9e du Jugement", "Augmente les d\u00e9g\u00e2ts de base du sort \u00c9p\u00e9e du Jugement de 10 (infini)"], "EffetsCritiques": ["32 \u00e0 37 (dommages Eau)", "\u00c9p\u00e9e du Jugement", "Enl\u00e8ve les effets du sort \u00c9p\u00e9e du Jugement", "Enl\u00e8ve les effets du sort \u00c9p\u00e9e du Jugement", "Augmente les d\u00e9g\u00e2ts de base du sort \u00c9p\u00e9e du Jugement de 10 (infini)"], "Autres": {"Probabilit\u00e9 de coup critique": "5%", "Nb. de lancers par tour": "1", "Port\u00e9e modifiable": "Non", "Ligne de vue": "Non", "Lancer en ligne": "Non", "Cellules libres": "Non"}}}, "Ferveur": {"img": "https://static.ankama.com/dofus/ng/img/../../../dofus/www/game/spells/55/sort_4065.png", "id": "14676", "nom_variante": "Menace", "1": {"PO_min": "1", "PO_max": "3", "PA": "3", "level": "30", "Effets": ["75% du niveau en bouclier (2 tours)", "15 \u00e0 17 (dommages Eau)"], "EffetsCritiques": ["75% du niveau en bouclier (2 tours)", "18 \u00e0 20 (dommages Eau)"], "Autres": {"Probabilit\u00e9 de coup critique": "25%", "Nb. de lancers par tour": "3", "Nb. de lancers par tour par joueur": "2", "Port\u00e9e modifiable": "Non", "Ligne de vue": "Oui", "Lancer en ligne": "Non", "Cellules libres": "Non", "Zone d'effet": "Croix de 1 case"}}, "desc": "Occasionne des dommages Eau. Applique des points de bouclier aux alli\u00e9s au contact de la cible.", "2": {"PO_min": "1", "PO_max": "3", "PA": "3", "level": "97", "Effets": ["75% du niveau en bouclier (2 tours)", "19 \u00e0 22 (dommages Eau)"], "EffetsCritiques": ["75% du niveau en bouclier (2 tours)", "23 \u00e0 26 (dommages Eau)"], "Autres": {"Probabilit\u00e9 de coup critique": "25%", "Nb. de lancers par tour": "3", "Nb. de lancers par tour par joueur": "2", "Port\u00e9e modifiable": "Non", "Ligne de vue": "Oui", "Lancer en ligne": "Non", "Cellules libres": "Non", "Zone d'effet": "Croix de 1 case"}}, "3": {"PO_min": "1", "PO_max": "3", "PA": "3", "level": "164", "Effets": ["75% du niveau en bouclier (2 tours)", "24 \u00e0 27 (dommages Eau)"], "EffetsCritiques": ["75% du niveau en bouclier (2 tours)", "29 \u00e0 32 (dommages Eau)"], "Autres": {"Probabilit\u00e9 de coup critique": "25%", "Nb. de lancers par tour": "3", "Nb. de lancers par tour par joueur": "2", "Port\u00e9e modifiable": "Non", "Ligne de vue": "Oui", "Lancer en ligne": "Non", "Cellules libres": "Non", "Zone d'effet": "Croix de 1 case"}}}, "Menace": {"img": "https://static.ankama.com/dofus/ng/img/../../../dofus/www/game/spells/55/sort_3730.png", "id": "13130", "nom_variante": "Ferveur", "1": {"PO_min": "0", "PO_max": "3", "PA": "3", "level": "140", "Effets": ["26 \u00e0 28 (dommages Eau)", "Attire de 2 case(s)", "50% du niveau en bouclier (2 tours)"], "EffetsCritiques": ["31 \u00e0 34 (dommages Eau)", "Attire de 2 case(s)", "50% du niveau en bouclier (2 tours)"], "Autres": {"Probabilit\u00e9 de coup critique": "5%", "Nb. de lancers par tour": "3", "Nb. de lancers par tour par joueur": "2", "Port\u00e9e modifiable": "Non", "Ligne de vue": "Oui", "Lancer en ligne": "Non", "Cellules libres": "Non"}}, "desc": "Occasionne des dommages Eau et attire la cible.\r\nLe lanceur gagne des points de bouclier.", "2": {"PO_min": "0", "PO_max": "3", "PA": "3", "level": "140", "Effets": ["26 \u00e0 28 (dommages Eau)", "Attire de 2 case(s)", "50% du niveau en bouclier (2 tours)"], "EffetsCritiques": ["31 \u00e0 34 (dommages Eau)", "Attire de 2 case(s)", "50% du niveau en bouclier (2 tours)"], "Autres": {"Probabilit\u00e9 de coup critique": "5%", "Nb. de lancers par tour": "3", "Nb. de lancers par tour par joueur": "2", "Port\u00e9e modifiable": "Non", "Ligne de vue": "Oui", "Lancer en ligne": "Non", "Cellules libres": "Non"}}}, "Friction": {"img": "https://static.ankama.com/dofus/ng/img/../../../dofus/www/game/spells/55/sort_148.png", "id": "13113", "nom_variante": "Coup pour coup", "1": {"PO_min": "0", "PO_max": "4", "PA": "2", "level": "35", "Effets": ["Frikt", "Attire de 1 case(s)"], "EffetsCritiques": [], "Autres": {"Nb. de tours entre deux lancers": "5", "Port\u00e9e modifiable": "Non", "Ligne de vue": "Non", "Lancer en ligne": "Non", "Cellules libres": "Non"}}, "desc": "Attire la cible d'une case.\r\nLa cible se rapproche ensuite de l'attaquant si elle re\u00e7oit des dommages issus de sorts pendant 2 tours.\r\nN\u00e9cessite d'\u00eatre align\u00e9 avec la cible.", "2": {"PO_min": "0", "PO_max": "4", "PA": "2", "level": "102", "Effets": ["Frikt", "Attire de 1 case(s)"], "EffetsCritiques": [], "Autres": {"Nb. de tours entre deux lancers": "4", "Port\u00e9e modifiable": "Non", "Ligne de vue": "Non", "Lancer en ligne": "Non", "Cellules libres": "Non"}}, "3": {"PO_min": "0", "PO_max": "5", "PA": "2", "level": "169", "Effets": ["Frikt", "Attire de 1 case(s)"], "EffetsCritiques": [], "Autres": {"Nb. de tours entre deux lancers": "3", "Port\u00e9e modifiable": "Non", "Ligne de vue": "Non", "Lancer en ligne": "Non", "Cellules libres": "Non"}}}, "Coup pour coup": {"img": "https://static.ankama.com/dofus/ng/img/../../../dofus/www/game/spells/55/sort_3744.png", "id": "13140", "nom_variante": "Friction", "1": {"PO_min": "1", "PO_max": "3", "PA": "2", "level": "145", "Effets": ["\u00c9tat 'Coup pour Coup' (2 tours)", "Coup pour Coup", "Repousse de 2 case(s)"], "EffetsCritiques": [], "Autres": {"Nb. de tours entre deux lancers": "3", "Port\u00e9e modifiable": "Non", "Ligne de vue": "Oui", "Lancer en ligne": "Non", "Cellules libres": "Non"}}, "desc": "Repousse un ennemi.\r\nLa cible est ensuite repouss\u00e9e de 2 cases \u00e0 chaque fois qu'elle attaque le lanceur pendant 2 tours.", "2": {"PO_min": "1", "PO_max": "3", "PA": "2", "level": "145", "Effets": ["\u00c9tat 'Coup pour Coup' (2 tours)", "Coup pour Coup", "Repousse de 2 case(s)"], "EffetsCritiques": [], "Autres": {"Nb. de tours entre deux lancers": "3", "Port\u00e9e modifiable": "Non", "Ligne de vue": "Oui", "Lancer en ligne": "Non", "Cellules libres": "Non"}}}, "Duel": {"img": "https://static.ankama.com/dofus/ng/img/../../../dofus/www/game/spells/55/sort_144.png", "id": "13109", "nom_variante": "Emprise", "1": {"PO_min": "1", "PO_max": "1", "PA": "3", "level": "40", "Effets": ["Duel", "\u00c9tat 'Invuln\u00e9rabilit\u00e9 \u00e0 Distance' (1 tour)", "\u00c9tat 'Invuln\u00e9rabilit\u00e9 \u00e0 Distance' (1 tour)", "\u00c9tat 'Pesanteur' (2 tours)", "\u00c9tat 'Pesanteur' (1 tour)", "-100 PM (2 tours)", "-100 PM (1 tour)"], "EffetsCritiques": [], "Autres": {"Nb. de tours entre deux lancers": "6", "Port\u00e9e modifiable": "Non", "Ligne de vue": "Non", "Lancer en ligne": "Non", "Cellules libres": "Non"}}, "desc": "Retire leurs PM \u00e0 la cible et au lanceur, leur applique l'\u00e9tat Pesanteur et les rend invuln\u00e9rable aux dommages \u00e0 distance.\r\nNe fonctionne que si lanc\u00e9 sur un ennemi.", "2": {"PO_min": "1", "PO_max": "1", "PA": "3", "level": "107", "Effets": ["Duel", "\u00c9tat 'Invuln\u00e9rabilit\u00e9 \u00e0 Distance' (1 tour)", "\u00c9tat 'Invuln\u00e9rabilit\u00e9 \u00e0 Distance' (1 tour)", "\u00c9tat 'Pesanteur' (2 tours)", "\u00c9tat 'Pesanteur' (1 tour)", "-100 PM (2 tours)", "-100 PM (1 tour)"], "EffetsCritiques": [], "Autres": {"Nb. de tours entre deux lancers": "5", "Port\u00e9e modifiable": "Non", "Ligne de vue": "Non", "Lancer en ligne": "Non", "Cellules libres": "Non"}}, "3": {"PO_min": "1", "PO_max": "1", "PA": "3", "level": "174", "Effets": ["Duel", "\u00c9tat 'Invuln\u00e9rabilit\u00e9 \u00e0 Distance' (1 tour)", "\u00c9tat 'Invuln\u00e9rabilit\u00e9 \u00e0 Distance' (1 tour)", "\u00c9tat 'Pesanteur' (2 tours)", "\u00c9tat 'Pesanteur' (1 tour)", "-100 PM (2 tours)", "-100 PM (1 tour)"], "EffetsCritiques": [], "Autres": {"Nb. de tours entre deux lancers": "4", "Port\u00e9e modifiable": "Non", "Ligne de vue": "Non", "Lancer en ligne": "Non", "Cellules libres": "Non"}}}, "Emprise": {"img": "https://static.ankama.com/dofus/ng/img/../../../dofus/www/game/spells/55/sort_3747.png", "id": "13141", "nom_variante": "Duel", "1": {"PO_min": "1", "PO_max": "1", "PA": "3", "level": "150", "Effets": ["\u00c9tat 'Invuln\u00e9rable' (1 tour)", "-100 PM (1 tour)"], "EffetsCritiques": [], "Autres": {"Nb. de tours entre deux lancers": "4", "Port\u00e9e modifiable": "Non", "Ligne de vue": "Non", "Lancer en ligne": "Non", "Cellules libres": "Non"}}, "desc": "Retire tous les PM de l'ennemi cibl\u00e9 mais le rend invuln\u00e9rable.", "2": {"PO_min": "1", "PO_max": "1", "PA": "3", "level": "150", "Effets": ["\u00c9tat 'Invuln\u00e9rable' (1 tour)", "-100 PM (1 tour)"], "EffetsCritiques": [], "Autres": {"Nb. de tours entre deux lancers": "4", "Port\u00e9e modifiable": "Non", "Ligne de vue": "Non", "Lancer en ligne": "Non", "Cellules libres": "Non"}}}, "Temp\u00eate de Puissance": {"img": "https://static.ankama.com/dofus/ng/img/../../../dofus/www/game/spells/55/sort_156.png", "id": "13121", "nom_variante": "Tumulte", "1": {"PO_min": "3", "PO_max": "5", "PA": "3", "level": "45", "Effets": ["Enl\u00e8ve les effets du sort Temp\u00eate de Puissance", "Enl\u00e8ve les effets du sort Temp\u00eate de Puissance", "17 \u00e0 20 (dommages Feu)", "17 \u00e0 20 (dommages Feu)", "\u00c9tat 'Temp\u00eate de Puissance 1' (infini)", "41 \u00e0 45 (dommages Feu)", "\u00c9tat 'Temp\u00eate de Puissance 2' (infini)"], "EffetsCritiques": ["Enl\u00e8ve les effets du sort Temp\u00eate de Puissance", "Enl\u00e8ve les effets du sort Temp\u00eate de Puissance", "20 \u00e0 23 (dommages Feu)", "20 \u00e0 23 (dommages Feu)", "\u00c9tat 'Temp\u00eate de Puissance 1' (infini)", "41 \u00e0 45 (dommages Feu)", "\u00c9tat 'Temp\u00eate de Puissance 2' (infini)"], "Autres": {"Probabilit\u00e9 de coup critique": "5%", "Nb. de lancers par tour": "3", "Nb. de lancers par tour par joueur": "2", "Port\u00e9e modifiable": "Non", "Ligne de vue": "Oui", "Lancer en ligne": "Non", "Cellules libres": "Non", "Zone d'effet": "Cercle de 63 cases"}}, "desc": "Occasionne des dommages Feu. Occasionne des dommages Feu suppl\u00e9mentaires sur la cible initiale lorsque le sort est lanc\u00e9 sur une autre cible. \r\n\r\nLes dommages suppl\u00e9mentaires lors du changement de cible sont augment\u00e9s si le sort a d'abord \u00e9t\u00e9 utilis\u00e9 deux fois sur la cible initiale.\r\n\r\nN'inflige pas de dommages aux alli\u00e9s.", "2": {"PO_min": "3", "PO_max": "5", "PA": "3", "level": "112", "Effets": ["Enl\u00e8ve les effets du sort Temp\u00eate de Puissance", "Enl\u00e8ve les effets du sort Temp\u00eate de Puissance", "22 \u00e0 26 (dommages Feu)", "22 \u00e0 26 (dommages Feu)", "\u00c9tat 'Temp\u00eate de Puissance 1' (infini)", "41 \u00e0 45 (dommages Feu)", "\u00c9tat 'Temp\u00eate de Puissance 2' (infini)"], "EffetsCritiques": ["Enl\u00e8ve les effets du sort Temp\u00eate de Puissance", "Enl\u00e8ve les effets du sort Temp\u00eate de Puissance", "27 \u00e0 31 (dommages Feu)", "27 \u00e0 31 (dommages Feu)", "\u00c9tat 'Temp\u00eate de Puissance 1' (infini)", "41 \u00e0 45 (dommages Feu)", "\u00c9tat 'Temp\u00eate de Puissance 2' (infini)"], "Autres": {"Probabilit\u00e9 de coup critique": "5%", "Nb. de lancers par tour": "3", "Nb. de lancers par tour par joueur": "2", "Port\u00e9e modifiable": "Non", "Ligne de vue": "Oui", "Lancer en ligne": "Non", "Cellules libres": "Non", "Zone d'effet": "Cercle de 63 cases"}}, "3": {"PO_min": "3", "PO_max": "5", "PA": "3", "level": "179", "Effets": ["Enl\u00e8ve les effets du sort Temp\u00eate de Puissance", "Enl\u00e8ve les effets du sort Temp\u00eate de Puissance", "27 \u00e0 31 (dommages Feu)", "27 \u00e0 31 (dommages Feu)", "\u00c9tat 'Temp\u00eate de Puissance 1' (infini)", "41 \u00e0 45 (dommages Feu)", "\u00c9tat 'Temp\u00eate de Puissance 2' (infini)"], "EffetsCritiques": ["Enl\u00e8ve les effets du sort Temp\u00eate de Puissance", "Enl\u00e8ve les effets du sort Temp\u00eate de Puissance", "32 \u00e0 37 (dommages Feu)", "32 \u00e0 37 (dommages Feu)", "\u00c9tat 'Temp\u00eate de Puissance 1' (infini)", "41 \u00e0 45 (dommages Feu)", "\u00c9tat 'Temp\u00eate de Puissance 2' (infini)"], "Autres": {"Probabilit\u00e9 de coup critique": "5%", "Nb. de lancers par tour": "3", "Nb. de lancers par tour par joueur": "2", "Port\u00e9e modifiable": "Non", "Ligne de vue": "Oui", "Lancer en ligne": "Non", "Cellules libres": "Non", "Zone d'effet": "Cercle de 63 cases"}}}, "Tumulte": {"img": "https://static.ankama.com/dofus/ng/img/../../../dofus/www/game/spells/55/sort_3738.png", "id": "13144", "nom_variante": "Temp\u00eate de Puissance", "1": {"PO_min": "2", "PO_max": "5", "PA": "4", "level": "155", "Effets": ["Tumulte", "19 \u00e0 21 (dommages Feu)", "Augmente les d\u00e9g\u00e2ts de base du sort Tumulte de 20"], "EffetsCritiques": ["Tumulte", "23 \u00e0 25 (dommages Feu)", "Augmente les d\u00e9g\u00e2ts de base du sort Tumulte de 20"], "Autres": {"Probabilit\u00e9 de coup critique": "5%", "Nb. de tours entre deux lancers": "1", "Port\u00e9e modifiable": "Non", "Ligne de vue": "Oui", "Lancer en ligne": "Non", "Cellules libres": "Non", "Zone d'effet": "Croix de 1 case"}}, "desc": "Occasionne des dommages Feu en zone.\r\nPlus le nombre de cibles ennemies est important, plus les dommages sont importants.", "2": {"PO_min": "2", "PO_max": "5", "PA": "4", "level": "155", "Effets": ["Tumulte", "19 \u00e0 21 (dommages Feu)", "Augmente les d\u00e9g\u00e2ts de base du sort Tumulte de 20"], "EffetsCritiques": ["Tumulte", "23 \u00e0 25 (dommages Feu)", "Augmente les d\u00e9g\u00e2ts de base du sort Tumulte de 20"], "Autres": {"Probabilit\u00e9 de coup critique": "5%", "Nb. de tours entre deux lancers": "1", "Port\u00e9e modifiable": "Non", "Ligne de vue": "Oui", "Lancer en ligne": "Non", "Cellules libres": "Non", "Zone d'effet": "Croix de 1 case"}}}, "\u00c9p\u00e9e C\u00e9leste": {"img": "https://static.ankama.com/dofus/ng/img/../../../dofus/www/game/spells/55/sort_157.png", "id": "13122", "nom_variante": "Z\u00e9nith", "1": {"PO_min": "0", "PO_max": "4", "PA": "4", "level": "50", "Effets": ["28 \u00e0 31 (dommages Air)"], "EffetsCritiques": ["34 \u00e0 37 (dommages Air)"], "Autres": {"Probabilit\u00e9 de coup critique": "15%", "Nb. de lancers par tour": "2", "Port\u00e9e modifiable": "Non", "Ligne de vue": "Oui", "Lancer en ligne": "Oui", "Cellules libres": "Non", "Zone d'effet": "Cercle de 2 cases"}}, "desc": "Occasionne des dommages Air en zone.", "2": {"PO_min": "0", "PO_max": "4", "PA": "4", "level": "117", "Effets": ["31 \u00e0 35 (dommages Air)"], "EffetsCritiques": ["38 \u00e0 42 (dommages Air)"], "Autres": {"Probabilit\u00e9 de coup critique": "15%", "Nb. de lancers par tour": "2", "Port\u00e9e modifiable": "Non", "Ligne de vue": "Oui", "Lancer en ligne": "Oui", "Cellules libres": "Non", "Zone d'effet": "Cercle de 2 cases"}}, "3": {"PO_min": "0", "PO_max": "4", "PA": "4", "level": "184", "Effets": ["36 \u00e0 40 (dommages Air)"], "EffetsCritiques": ["43 \u00e0 48 (dommages Air)"], "Autres": {"Probabilit\u00e9 de coup critique": "15%", "Nb. de lancers par tour": "2", "Port\u00e9e modifiable": "Non", "Ligne de vue": "Oui", "Lancer en ligne": "Oui", "Cellules libres": "Non", "Zone d'effet": "Cercle de 2 cases"}}}, "Z\u00e9nith": {"img": "https://static.ankama.com/dofus/ng/img/../../../dofus/www/game/spells/55/sort_3737.png", "id": "13145", "nom_variante": "\u00c9p\u00e9e C\u00e9leste", "1": {"PO_min": "1", "PO_max": "3", "PA": "5", "level": "160", "Effets": ["29 \u00e0 31 (dommages Air)", "57 \u00e0 63 (dommages Air)"], "EffetsCritiques": ["34 \u00e0 38 (dommages Air)", "69 \u00e0 75 (dommages Air)"], "Autres": {"Probabilit\u00e9 de coup critique": "5%", "Nb. de lancers par tour": "1", "Port\u00e9e modifiable": "Non", "Ligne de vue": "Oui", "Lancer en ligne": "Oui", "Cellules libres": "Non", "Zone d'effet": "Ligne de 4 cases"}}, "desc": "Occasionne des dommages Air en zone. \r\nOccasionne des dommages Air suppl\u00e9mentaires selon les PM du lanceur : moins le lanceur a utilis\u00e9 de PM pendant son tour de jeu, plus les dommages suppl\u00e9mentaires seront importants.", "2": {"PO_min": "1", "PO_max": "3", "PA": "5", "level": "160", "Effets": ["29 \u00e0 31 (dommages Air)", "57 \u00e0 63 (dommages Air)"], "EffetsCritiques": ["34 \u00e0 38 (dommages Air)", "69 \u00e0 75 (dommages Air)"], "Autres": {"Probabilit\u00e9 de coup critique": "5%", "Nb. de lancers par tour": "1", "Port\u00e9e modifiable": "Non", "Ligne de vue": "Oui", "Lancer en ligne": "Oui", "Cellules libres": "Non", "Zone d'effet": "Ligne de 4 cases"}}}, "Puissance": {"img": "https://static.ankama.com/dofus/ng/img/../../../dofus/www/game/spells/55/sort_153.png", "id": "13118", "nom_variante": "Vertu", "1": {"PO_min": "0", "PO_max": "2", "PA": "3", "level": "55", "Effets": ["100 Puissance (3 tours)"], "EffetsCritiques": ["120 Puissance (3 tours)"], "Autres": {"Probabilit\u00e9 de coup critique": "15%", "Nb. de tours entre deux lancers": "4", "Port\u00e9e modifiable": "Non", "Ligne de vue": "Oui", "Lancer en ligne": "Non", "Cellules libres": "Non"}}, "desc": "Augmente la Puissance de la cible.", "2": {"PO_min": "0", "PO_max": "4", "PA": "3", "level": "122", "Effets": ["200 Puissance (3 tours)"], "EffetsCritiques": ["240 Puissance (3 tours)"], "Autres": {"Probabilit\u00e9 de coup critique": "15%", "Nb. de tours entre deux lancers": "4", "Port\u00e9e modifiable": "Non", "Ligne de vue": "Oui", "Lancer en ligne": "Non", "Cellules libres": "Non"}}, "3": {"PO_min": "0", "PO_max": "6", "PA": "3", "level": "189", "Effets": ["300 Puissance (3 tours)"], "EffetsCritiques": ["350 Puissance (3 tours)"], "Autres": {"Probabilit\u00e9 de coup critique": "15%", "Nb. de tours entre deux lancers": "4", "Port\u00e9e modifiable": "Non", "Ligne de vue": "Oui", "Lancer en ligne": "Non", "Cellules libres": "Non"}}}, "Vertu": {"img": "https://static.ankama.com/dofus/ng/img/../../../dofus/www/game/spells/55/sort_3739.png", "id": "13142", "nom_variante": "Puissance", "1": {"PO_min": "0", "PO_max": "0", "PA": "3", "level": "165", "Effets": ["500% du niveau en bouclier (2 tours)", "-150 Puissance (2 tours)"], "EffetsCritiques": [], "Autres": {"Nb. de tours entre deux lancers": "3", "Port\u00e9e modifiable": "Non", "Ligne de vue": "Non", "Lancer en ligne": "Non", "Cellules libres": "Non", "Zone d'effet": "Croix de 1 case"}}, "desc": "Applique un bouclier zone mais r\u00e9duit la Puissance du lanceur.", "2": {"PO_min": "0", "PO_max": "0", "PA": "3", "level": "165", "Effets": ["500% du niveau en bouclier (2 tours)", "-150 Puissance (2 tours)"], "EffetsCritiques": [], "Autres": {"Nb. de tours entre deux lancers": "3", "Port\u00e9e modifiable": "Non", "Ligne de vue": "Non", "Lancer en ligne": "Non", "Cellules libres": "Non", "Zone d'effet": "Croix de 1 case"}}}, "Pr\u00e9cipitation": {"img": "https://static.ankama.com/dofus/ng/img/../../../dofus/www/game/spells/55/sort_149.png", "id": "13114", "nom_variante": "Agitation", "1": {"PO_min": "0", "PO_max": "2", "PA": "2", "level": "60", "Effets": ["5 PA (1 tour)", "\u00c9tat 'Pr\u00e9cipit\u00e9' (1 tour)", "-3 PA (1 tour)"], "EffetsCritiques": [], "Autres": {"Nb. de tours entre deux lancers": "4", "Port\u00e9e modifiable": "Non", "Ligne de vue": "Oui", "Lancer en ligne": "Non", "Cellules libres": "Non"}}, "desc": "Augmente les PA de la cible pour le tour en cours mais lui retire des PA le tour suivant.\r\nInterdit l'utilisation des armes et du sort Col\u00e8re de Iop.", "2": {"PO_min": "0", "PO_max": "4", "PA": "2", "level": "127", "Effets": ["5 PA (1 tour)", "\u00c9tat 'Pr\u00e9cipit\u00e9' (1 tour)", "-3 PA (1 tour)"], "EffetsCritiques": [], "Autres": {"Nb. de tours entre deux lancers": "3", "Port\u00e9e modifiable": "Non", "Ligne de vue": "Oui", "Lancer en ligne": "Non", "Cellules libres": "Non"}}, "3": {"PO_min": "0", "PO_max": "6", "PA": "2", "level": "194", "Effets": ["5 PA (1 tour)", "\u00c9tat 'Pr\u00e9cipit\u00e9' (1 tour)", "-3 PA (1 tour)"], "EffetsCritiques": [], "Autres": {"Nb. de tours entre deux lancers": "2", "Port\u00e9e modifiable": "Non", "Ligne de vue": "Oui", "Lancer en ligne": "Non", "Cellules libres": "Non"}}}, "Agitation": {"img": "https://static.ankama.com/dofus/ng/img/../../../dofus/www/game/spells/55/sort_3743.png", "id": "13143", "nom_variante": "Pr\u00e9cipitation", "1": {"PO_min": "0", "PO_max": "5", "PA": "2", "level": "170", "Effets": ["2 PM (1 tour)", "\u00c9tat 'Intaclable' (1 tour)"], "EffetsCritiques": [], "Autres": {"Nb. de tours entre deux lancers": "2", "Port\u00e9e modifiable": "Non", "Ligne de vue": "Oui", "Lancer en ligne": "Non", "Cellules libres": "Non"}}, "desc": "Augmente les PM et rend Intaclable pour le tour en cours.", "2": {"PO_min": "0", "PO_max": "5", "PA": "2", "level": "170", "Effets": ["2 PM (1 tour)", "\u00c9tat 'Intaclable' (1 tour)"], "EffetsCritiques": [], "Autres": {"Nb. de tours entre deux lancers": "2", "Port\u00e9e modifiable": "Non", "Ligne de vue": "Oui", "Lancer en ligne": "Non", "Cellules libres": "Non"}}}, "Fustigation": {"img": "https://static.ankama.com/dofus/ng/img/../../../dofus/www/game/spells/55/sort_4150.png", "id": "14818", "nom_variante": "Endurance", "1": {"PO_min": "1", "PO_max": "1", "PA": "4", "level": "65", "Effets": ["27 \u00e0 30 (dommages Eau)", "-20 Fuite (1 tour)"], "EffetsCritiques": ["32 \u00e0 36 (dommages Eau)", "-25 Fuite (1 tour)"], "Autres": {"Probabilit\u00e9 de coup critique": "10%", "Nb. de lancers par tour": "2", "Port\u00e9e modifiable": "Non", "Ligne de vue": "Oui", "Lancer en ligne": "Oui", "Cellules libres": "Non", "Zone d'effet": "Demi-cercle de 1 case"}}, "desc": "Occasionne des dommages Eau et applique un malus de Fuite.", "2": {"PO_min": "1", "PO_max": "1", "PA": "4", "level": "131", "Effets": ["32 \u00e0 36 (dommages Eau)", "-30 Fuite (1 tour)"], "EffetsCritiques": ["39 \u00e0 43 (dommages Eau)", "-35 Fuite (1 tour)"], "Autres": {"Probabilit\u00e9 de coup critique": "10%", "Nb. de lancers par tour": "2", "Port\u00e9e modifiable": "Non", "Ligne de vue": "Oui", "Lancer en ligne": "Oui", "Cellules libres": "Non", "Zone d'effet": "Demi-cercle de 1 case"}}, "3": {"PO_min": "1", "PO_max": "1", "PA": "4", "level": "198", "Effets": ["36 \u00e0 40 (dommages Eau)", "-40 Fuite (1 tour)"], "EffetsCritiques": ["43 \u00e0 48 (dommages Eau)", "-50 Fuite (1 tour)"], "Autres": {"Probabilit\u00e9 de coup critique": "10%", "Nb. de lancers par tour": "2", "Port\u00e9e modifiable": "Non", "Ligne de vue": "Oui", "Lancer en ligne": "Oui", "Cellules libres": "Non", "Zone d'effet": "Demi-cercle de 1 case"}}}, "Endurance": {"img": "https://static.ankama.com/dofus/ng/img/../../../dofus/www/game/spells/55/sort_3729.png", "id": "13133", "nom_variante": "Fustigation", "1": {"PO_min": "0", "PO_max": "1", "PA": "3", "level": "175", "Effets": ["30 \u00e0 34 (dommages Eau)", "75% du niveau en bouclier (2 tours)"], "EffetsCritiques": ["36 \u00e0 41 (dommages Eau)", "75% du niveau en bouclier (2 tours)"], "Autres": {"Probabilit\u00e9 de coup critique": "15%", "Nb. de lancers par tour": "3", "Nb. de lancers par tour par joueur": "2", "Port\u00e9e modifiable": "Non", "Ligne de vue": "Non", "Lancer en ligne": "Non", "Cellules libres": "Non"}}, "desc": "Occasionne des dommages Eau.\r\nApplique des points de bouclier au lanceur.", "2": {"PO_min": "0", "PO_max": "1", "PA": "3", "level": "175", "Effets": ["30 \u00e0 34 (dommages Eau)", "75% du niveau en bouclier (2 tours)"], "EffetsCritiques": ["36 \u00e0 41 (dommages Eau)", "75% du niveau en bouclier (2 tours)"], "Autres": {"Probabilit\u00e9 de coup critique": "15%", "Nb. de lancers par tour": "3", "Nb. de lancers par tour par joueur": "2", "Port\u00e9e modifiable": "Non", "Ligne de vue": "Non", "Lancer en ligne": "Non", "Cellules libres": "Non"}}}, "\u00c9p\u00e9e de Iop": {"img": "https://static.ankama.com/dofus/ng/img/../../../dofus/www/game/spells/55/sort_160.png", "id": "13125", "nom_variante": "Pugilat", "1": {"PO_min": "1", "PO_max": "5", "PA": "4", "level": "70", "Effets": ["30 \u00e0 33 (dommages Terre)"], "EffetsCritiques": ["36 \u00e0 39 (dommages Terre)"], "Autres": {"Probabilit\u00e9 de coup critique": "15%", "Nb. de lancers par tour": "2", "Port\u00e9e modifiable": "Non", "Ligne de vue": "Oui", "Lancer en ligne": "Oui", "Cellules libres": "Non", "Zone d'effet": "Croix de 3 cases"}}, "desc": "Occasionne des dommages Terre en croix.", "2": {"PO_min": "1", "PO_max": "6", "PA": "4", "level": "137", "Effets": ["37 \u00e0 41 (dommages Terre)"], "EffetsCritiques": ["44 \u00e0 49 (dommages Terre)"], "Autres": {"Probabilit\u00e9 de coup critique": "15%", "Nb. de lancers par tour": "2", "Port\u00e9e modifiable": "Non", "Ligne de vue": "Oui", "Lancer en ligne": "Oui", "Cellules libres": "Non", "Zone d'effet": "Croix de 3 cases"}}, "3": {"PO_min": "1", "PO_max": "5", "PA": "4", "level": "70", "Effets": ["30 \u00e0 33 (dommages Terre)"], "EffetsCritiques": ["36 \u00e0 39 (dommages Terre)"], "Autres": {"Probabilit\u00e9 de coup critique": "15%", "Nb. de lancers par tour": "2", "Port\u00e9e modifiable": "Non", "Ligne de vue": "Oui", "Lancer en ligne": "Oui", "Cellules libres": "Non", "Zone d'effet": "Croix de 3 cases"}}}, "Pugilat": {"img": "https://static.ankama.com/dofus/ng/img/../../../dofus/www/game/spells/55/sort_3734.png", "id": "13146", "nom_variante": "\u00c9p\u00e9e de Iop", "1": {"PO_min": "1", "PO_max": "6", "PA": "2", "level": "180", "Effets": ["9 \u00e0 11 (dommages Terre)", "Augmente les d\u00e9g\u00e2ts de base du sort Pugilat de 15"], "EffetsCritiques": ["11 \u00e0 13 (dommages Terre)", "Augmente les d\u00e9g\u00e2ts de base du sort Pugilat de 18"], "Autres": {"Probabilit\u00e9 de coup critique": "5%", "Nb. de lancers par tour": "4", "Nb. de lancers par tour par joueur": "1", "Port\u00e9e modifiable": "Non", "Ligne de vue": "Oui", "Lancer en ligne": "Non", "Cellules libres": "Non", "Zone d'effet": "Cercle de 2 cases"}}, "desc": "Occasionne des dommages Terre en zone.\r\nLes dommages sont augment\u00e9s pendant 1 tour apr\u00e8s chaque lancer.", "2": {"PO_min": "1", "PO_max": "6", "PA": "2", "level": "180", "Effets": ["9 \u00e0 11 (dommages Terre)", "Augmente les d\u00e9g\u00e2ts de base du sort Pugilat de 15"], "EffetsCritiques": ["11 \u00e0 13 (dommages Terre)", "Augmente les d\u00e9g\u00e2ts de base du sort Pugilat de 18"], "Autres": {"Probabilit\u00e9 de coup critique": "5%", "Nb. de lancers par tour": "4", "Nb. de lancers par tour par joueur": "1", "Port\u00e9e modifiable": "Non", "Ligne de vue": "Oui", "Lancer en ligne": "Non", "Cellules libres": "Non", "Zone d'effet": "Cercle de 2 cases"}}}, "Vitalit\u00e9": {"img": "https://static.ankama.com/dofus/ng/img/../../../dofus/www/game/spells/55/sort_155.png", "id": "13120", "nom_variante": "Vindicte", "1": {"PO_min": "0", "PO_max": "2", "PA": "3", "level": "75", "Effets": ["16% Vitalit\u00e9 (4 tours)"], "EffetsCritiques": ["18% Vitalit\u00e9 (4 tours)"], "Autres": {"Probabilit\u00e9 de coup critique": "25%", "Nb. de tours entre deux lancers": "2", "Port\u00e9e modifiable": "Non", "Ligne de vue": "Oui", "Lancer en ligne": "Non", "Cellules libres": "Non"}}, "desc": "Augmente temporairement la Vitalit\u00e9 de la cible en pourcentage.\r\nLe bonus de Vitalit\u00e9 est divis\u00e9 par 2 sur les cibles autres que le lanceur.", "2": {"PO_min": "0", "PO_max": "6", "PA": "3", "level": "142", "Effets": ["20% Vitalit\u00e9 (4 tours)"], "EffetsCritiques": ["22% Vitalit\u00e9 (4 tours)"], "Autres": {"Probabilit\u00e9 de coup critique": "25%", "Nb. de tours entre deux lancers": "2", "Port\u00e9e modifiable": "Non", "Ligne de vue": "Oui", "Lancer en ligne": "Non", "Cellules libres": "Non"}}, "3": {"PO_min": "0", "PO_max": "2", "PA": "3", "level": "75", "Effets": ["16% Vitalit\u00e9 (4 tours)"], "EffetsCritiques": ["18% Vitalit\u00e9 (4 tours)"], "Autres": {"Probabilit\u00e9 de coup critique": "25%", "Nb. de tours entre deux lancers": "2", "Port\u00e9e modifiable": "Non", "Ligne de vue": "Oui", "Lancer en ligne": "Non", "Cellules libres": "Non"}}}, "Vindicte": {"img": "https://static.ankama.com/dofus/ng/img/../../../dofus/www/game/spells/55/sort_4066.png", "id": "14677", "nom_variante": "Vitalit\u00e9", "1": {"PO_min": "1", "PO_max": "3", "PA": "3", "level": "185", "Effets": ["30% \u00c9rosion (2 tours)"], "EffetsCritiques": [], "Autres": {"Nb. de lancers par tour": "1", "Nb. de lancers par tour par joueur": "1", "Port\u00e9e modifiable": "Non", "Ligne de vue": "Oui", "Lancer en ligne": "Non", "Cellules libres": "Non"}}, "desc": "Applique un malus d'\u00c9rosion.", "2": {"PO_min": "1", "PO_max": "3", "PA": "3", "level": "185", "Effets": ["30% \u00c9rosion (2 tours)"], "EffetsCritiques": [], "Autres": {"Nb. de lancers par tour": "1", "Nb. de lancers par tour par joueur": "1", "Port\u00e9e modifiable": "Non", "Ligne de vue": "Oui", "Lancer en ligne": "Non", "Cellules libres": "Non"}}}, "\u00c9p\u00e9e du Destin": {"img": "https://static.ankama.com/dofus/ng/img/../../../dofus/www/game/spells/55/sort_146.png", "id": "13111", "nom_variante": "Tann\u00e9e", "1": {"PO_min": "1", "PO_max": "1", "PA": "4", "level": "80", "Effets": ["31 \u00e0 34 (dommages Feu)", "Augmente les d\u00e9g\u00e2ts de base du sort \u00c9p\u00e9e du Destin de 30 (1 tour)"], "EffetsCritiques": ["37 \u00e0 40 (dommages Feu)", "Augmente les d\u00e9g\u00e2ts de base du sort \u00c9p\u00e9e du Destin de 35 (1 tour)"], "Autres": {"Probabilit\u00e9 de coup critique": "25%", "Nb. de tours entre deux lancers": "2", "Port\u00e9e modifiable": "Non", "Ligne de vue": "Oui", "Lancer en ligne": "Oui", "Cellules libres": "Non"}}, "desc": "Occasionne des dommages Feu.\r\nLes dommages sont augment\u00e9s \u00e0 partir du second lancer.", "2": {"PO_min": "1", "PO_max": "1", "PA": "4", "level": "147", "Effets": ["38 \u00e0 42 (dommages Feu)", "Augmente les d\u00e9g\u00e2ts de base du sort \u00c9p\u00e9e du Destin de 40 (1 tour)"], "EffetsCritiques": ["46 \u00e0 50 (dommages Feu)", "Augmente les d\u00e9g\u00e2ts de base du sort \u00c9p\u00e9e du Destin de 45 (1 tour)"], "Autres": {"Probabilit\u00e9 de coup critique": "25%", "Nb. de tours entre deux lancers": "2", "Port\u00e9e modifiable": "Non", "Ligne de vue": "Oui", "Lancer en ligne": "Oui", "Cellules libres": "Non"}}, "3": {"PO_min": "1", "PO_max": "1", "PA": "4", "level": "80", "Effets": ["31 \u00e0 34 (dommages Feu)", "Augmente les d\u00e9g\u00e2ts de base du sort \u00c9p\u00e9e du Destin de 30 (1 tour)"], "EffetsCritiques": ["37 \u00e0 40 (dommages Feu)", "Augmente les d\u00e9g\u00e2ts de base du sort \u00c9p\u00e9e du Destin de 35 (1 tour)"], "Autres": {"Probabilit\u00e9 de coup critique": "25%", "Nb. de tours entre deux lancers": "2", "Port\u00e9e modifiable": "Non", "Ligne de vue": "Oui", "Lancer en ligne": "Oui", "Cellules libres": "Non"}}}, "Tann\u00e9e": {"img": "https://static.ankama.com/dofus/ng/img/../../../dofus/www/game/spells/55/sort_3732.png", "id": "13131", "nom_variante": "\u00c9p\u00e9e du Destin", "1": {"PO_min": "1", "PO_max": "7", "PA": "4", "level": "190", "Effets": ["30 \u00e0 34 (dommages Air)", "-3 PM (1 tour)"], "EffetsCritiques": ["36 \u00e0 41 (dommages Air)", "-3 PM (1 tour)"], "Autres": {"Probabilit\u00e9 de coup critique": "5%", "Nb. de lancers par tour": "2", "Port\u00e9e modifiable": "Non", "Ligne de vue": "Oui", "Lancer en ligne": "Oui", "Cellules libres": "Non", "Zone d'effet": "Ligne perpendiculaire de 1 case"}}, "desc": "Occasionne des dommages Air en zone et retire des PM.", "2": {"PO_min": "1", "PO_max": "7", "PA": "4", "level": "190", "Effets": ["30 \u00e0 34 (dommages Air)", "-3 PM (1 tour)"], "EffetsCritiques": ["36 \u00e0 41 (dommages Air)", "-3 PM (1 tour)"], "Autres": {"Probabilit\u00e9 de coup critique": "5%", "Nb. de lancers par tour": "2", "Port\u00e9e modifiable": "Non", "Ligne de vue": "Oui", "Lancer en ligne": "Oui", "Cellules libres": "Non", "Zone d'effet": "Ligne perpendiculaire de 1 case"}}}, "Fendoir": {"img": "https://static.ankama.com/dofus/ng/img/../../../dofus/www/game/spells/55/sort_3728.png", "id": "13134", "nom_variante": "Sentence", "1": {"PO_min": "0", "PO_max": "3", "PA": "5", "level": "85", "Effets": ["Fendoir", "40 \u00e0 45 (dommages Eau)", "50% du niveau en bouclier (2 tours)"], "EffetsCritiques": ["Fendoir", "48 \u00e0 54 (dommages Eau)", "50% du niveau en bouclier (2 tours)"], "Autres": {"Probabilit\u00e9 de coup critique": "25%", "Nb. de lancers par tour": "2", "Port\u00e9e modifiable": "Non", "Ligne de vue": "Oui", "Lancer en ligne": "Non", "Cellules libres": "Non", "Zone d'effet": "Croix de 1 case"}}, "desc": "Occasionne des dommages Eau en zone.\r\nApplique des points de bouclier pour chaque ennemi touch\u00e9.", "2": {"PO_min": "0", "PO_max": "4", "PA": "5", "level": "152", "Effets": ["Fendoir", "47 \u00e0 53 (dommages Eau)", "50% du niveau en bouclier (2 tours)"], "EffetsCritiques": ["Fendoir", "56 \u00e0 64 (dommages Eau)", "50% du niveau en bouclier (2 tours)"], "Autres": {"Probabilit\u00e9 de coup critique": "25%", "Nb. de lancers par tour": "2", "Port\u00e9e modifiable": "Non", "Ligne de vue": "Oui", "Lancer en ligne": "Non", "Cellules libres": "Non", "Zone d'effet": "Croix de 1 case"}}, "3": {"PO_min": "0", "PO_max": "3", "PA": "5", "level": "85", "Effets": ["Fendoir", "40 \u00e0 45 (dommages Eau)", "50% du niveau en bouclier (2 tours)"], "EffetsCritiques": ["Fendoir", "48 \u00e0 54 (dommages Eau)", "50% du niveau en bouclier (2 tours)"], "Autres": {"Probabilit\u00e9 de coup critique": "25%", "Nb. de lancers par tour": "2", "Port\u00e9e modifiable": "Non", "Ligne de vue": "Oui", "Lancer en ligne": "Non", "Cellules libres": "Non", "Zone d'effet": "Croix de 1 case"}}}, "Sentence": {"img": "https://static.ankama.com/dofus/ng/img/../../../dofus/www/game/spells/55/sort_3746.png", "id": "13147", "nom_variante": "Fendoir", "1": {"PO_min": "1", "PO_max": "6", "PA": "2", "level": "195", "Effets": ["13 \u00e0 16 (dommages Feu)", "\u00c9tat 'Sentence' (1 tour)", "Sentence", "28 \u00e0 32 (dommages Feu)"], "EffetsCritiques": ["16 \u00e0 19 (dommages Feu)", "\u00c9tat 'Sentence' (1 tour)", "Sentence", "28 \u00e0 32 (dommages Feu)"], "Autres": {"Probabilit\u00e9 de coup critique": "25%", "Nb. de lancers par tour": "3", "Nb. de lancers par tour par joueur": "1", "Port\u00e9e modifiable": "Oui", "Ligne de vue": "Oui", "Lancer en ligne": "Non", "Cellules libres": "Non", "Zone d'effet": "Cercle de 2 cases"}}, "desc": "Occasionne des dommages Feu.\r\nOccasionne des dommages Feu suppl\u00e9mentaires aux ennemis \u00e0 proximit\u00e9 de la cible (2 cases ou moins) \u00e0 la fin de son tour.", "2": {"PO_min": "1", "PO_max": "6", "PA": "2", "level": "195", "Effets": ["13 \u00e0 16 (dommages Feu)", "\u00c9tat 'Sentence' (1 tour)", "Sentence", "28 \u00e0 32 (dommages Feu)"], "EffetsCritiques": ["16 \u00e0 19 (dommages Feu)", "\u00c9tat 'Sentence' (1 tour)", "Sentence", "28 \u00e0 32 (dommages Feu)"], "Autres": {"Probabilit\u00e9 de coup critique": "25%", "Nb. de lancers par tour": "3", "Nb. de lancers par tour par joueur": "1", "Port\u00e9e modifiable": "Oui", "Ligne de vue": "Oui", "Lancer en ligne": "Non", "Cellules libres": "Non", "Zone d'effet": "Cercle de 2 cases"}}}, "Col\u00e8re de Iop": {"img": "https://static.ankama.com/dofus/ng/img/../../../dofus/www/game/spells/55/sort_159.png", "id": "13124", "nom_variante": "Fureur", "1": {"PO_min": "1", "PO_max": "1", "PA": "7", "level": "90", "Effets": ["65 \u00e0 80 (dommages Terre)", "Augmente les d\u00e9g\u00e2ts de base du sort Col\u00e8re de Iop de 90 (1 tour)"], "EffetsCritiques": ["78 \u00e0 96 (dommages Terre)", "Augmente les d\u00e9g\u00e2ts de base du sort Col\u00e8re de Iop de 100 (1 tour)"], "Autres": {"Probabilit\u00e9 de coup critique": "25%", "Nb. de tours entre deux lancers": "3", "Port\u00e9e modifiable": "Non", "Ligne de vue": "Oui", "Lancer en ligne": "Non", "Cellules libres": "Non"}}, "desc": "Occasionne des dommages Terre.\r\nAugmente les dommages du sort au troisi\u00e8me tour apr\u00e8s son lancer.", "2": {"PO_min": "1", "PO_max": "1", "PA": "7", "level": "157", "Effets": ["Augmente les d\u00e9g\u00e2ts de base du sort Col\u00e8re de Iop de 110 (1 tour)", "81 \u00e0 100 (dommages Terre)"], "EffetsCritiques": ["Augmente les d\u00e9g\u00e2ts de base du sort Col\u00e8re de Iop de 120 (1 tour)", "97 \u00e0 120 (dommages Terre)"], "Autres": {"Probabilit\u00e9 de coup critique": "25%", "Nb. de tours entre deux lancers": "3", "Port\u00e9e modifiable": "Non", "Ligne de vue": "Oui", "Lancer en ligne": "Non", "Cellules libres": "Non"}}, "3": {"PO_min": "1", "PO_max": "1", "PA": "7", "level": "90", "Effets": ["65 \u00e0 80 (dommages Terre)", "Augmente les d\u00e9g\u00e2ts de base du sort Col\u00e8re de Iop de 90 (1 tour)"], "EffetsCritiques": ["78 \u00e0 96 (dommages Terre)", "Augmente les d\u00e9g\u00e2ts de base du sort Col\u00e8re de Iop de 100 (1 tour)"], "Autres": {"Probabilit\u00e9 de coup critique": "25%", "Nb. de tours entre deux lancers": "3", "Port\u00e9e modifiable": "Non", "Ligne de vue": "Oui", "Lancer en ligne": "Non", "Cellules libres": "Non"}}}, "Fureur": {"img": "https://static.ankama.com/dofus/ng/img/../../../dofus/www/game/spells/55/sort_3735.png", "id": "13156", "nom_variante": "Col\u00e8re de Iop", "1": {"PO_min": "1", "PO_max": "1", "PA": "3", "level": "200", "Effets": ["Fureur", "Fureur", "28 \u00e0 32 (dommages Terre)", "Augmente les d\u00e9g\u00e2ts de base du sort Fureur de 20 (2 tours)", "\u00c9tat 'Fureur Iop' (2 tours)", "Augmente les d\u00e9g\u00e2ts de base du sort Fureur de 40 (2 tours)", "Augmente les d\u00e9g\u00e2ts de base du sort Fureur de 20 (2 tours)"], "EffetsCritiques": ["Fureur", "Fureur", "34 \u00e0 38 (dommages Terre)", "Augmente les d\u00e9g\u00e2ts de base du sort Fureur de 20 (2 tours)", "\u00c9tat 'Fureur Iop' (2 tours)", "Augmente les d\u00e9g\u00e2ts de base du sort Fureur de 40 (2 tours)", "Augmente les d\u00e9g\u00e2ts de base du sort Fureur de 20 (2 tours)"], "Autres": {"Probabilit\u00e9 de coup critique": "5%", "Nb. de lancers par tour": "1", "Port\u00e9e modifiable": "Non", "Ligne de vue": "Non", "Lancer en ligne": "Non", "Cellules libres": "Non"}}, "desc": "Occasionne des dommages Terre.\r\nLes dommages sont augment\u00e9s \u00e0 chaque lancer du sort, mais ce bonus est perdu si le sort n'est pas relanc\u00e9.", "2": {"PO_min": "1", "PO_max": "1", "PA": "3", "level": "200", "Effets": ["Fureur", "Fureur", "28 \u00e0 32 (dommages Terre)", "Augmente les d\u00e9g\u00e2ts de base du sort Fureur de 20 (2 tours)", "\u00c9tat 'Fureur Iop' (2 tours)", "Augmente les d\u00e9g\u00e2ts de base du sort Fureur de 40 (2 tours)", "Augmente les d\u00e9g\u00e2ts de base du sort Fureur de 20 (2 tours)"], "EffetsCritiques": ["Fureur", "Fureur", "34 \u00e0 38 (dommages Terre)", "Augmente les d\u00e9g\u00e2ts de base du sort Fureur de 20 (2 tours)", "\u00c9tat 'Fureur Iop' (2 tours)", "Augmente les d\u00e9g\u00e2ts de base du sort Fureur de 40 (2 tours)", "Augmente les d\u00e9g\u00e2ts de base du sort Fureur de 20 (2 tours)"], "Autres": {"Probabilit\u00e9 de coup critique": "5%", "Nb. de lancers par tour": "1", "Port\u00e9e modifiable": "Non", "Ligne de vue": "Non", "Lancer en ligne": "Non", "Cellules libres": "Non"}}}}